noteist/__init__.py
noteist/__main__.py
noteist/cli.py
noteist/config_app.py
noteist/todoist_client.py
noteist-0.7.2.dist-info/WHEEL
noteist-0.7.2.dist-info/entry_points.txt
noteist-0.7.2.dist-info/METADATA
noteist-0.7.2.dist-info/RECORD
