Metadata-Version: 2.3
Name: noteist
Version: 0.7.2
Summary: Output a Markdown formatted report of completed tasks in Todoist.
Classifier: Programming Language :: Python :: 3.9
Classifier: Programming Language :: Python :: 3.10
Classifier: Programming Language :: Python :: 3.11
Classifier: Programming Language :: Python :: 3.12
Classifier: Programming Language :: Python :: 3.13
Classifier: License :: OSI Approved :: MIT License
Classifier: Operating System :: OS Independent
Classifier: Intended Audience :: Developers
Classifier: Intended Audience :: End Users/Desktop
Classifier: Topic :: Utilities
Classifier: Development Status :: 3 - Alpha
Requires-Dist: dateparser>=1.2.2
Requires-Dist: httpx>=0.28.1
Requires-Dist: toml>=0.10.2
Requires-Dist: typer>=0.16.0
Requires-Python: >=3.9
Project-URL: Documentation, https://github.com/epicserve/noteist
Project-URL: Source, https://github.com/epicserve/noteist
